{
  "sections": [
    {
      "callNumber": 5816,
      "sectionNumber": "01",
      "times": [
        {
          "start": 1430,
          "end": 1545,
          "startDate": "2026-01-26",
          "endDate": "2026-05-26",
          "day": [1, 3],
          "id": "1",
          "printTopic": false,
          "classroom": "HN-531",
          "topic": "",
          "freeFormatTopic": "",
          "code": "",
          "_ignoreSort": true,
          "timeBlockId": "ihlC5eN6"
        }
      ],
      "instructionMode": "In Person",
      "enrollment": 40,
      "maxEnrollment": 40,
      "startDate": "2026-01-26",
      "endDate": "2026-05-26"
    },
    {
      "callNumber": 5815,
      "sectionNumber": "02",
      "times": [
        {
          "start": 1000,
          "end": 1115,
          "startDate": "2026-01-26",
          "endDate": "2026-05-26",
          "day": [1, 3],
          "id": "1",
          "printTopic": false,
          "classroom": "HW-W113",
          "topic": "",
          "freeFormatTopic": "",
          "code": "",
          "_ignoreSort": true,
          "timeBlockId": null
        }
      ],
      "instructionMode": "In Person",
      "enrollment": 40,
      "maxEnrollment": 40,
      "startDate": "2026-01-26",
      "endDate": "2026-05-26"
    }
  ],
  "professors": {
    "24009111": {
      "_id": "24009111",
      "firstName": "Yuan",
      "id": "24009111",
      "lastName": "Yin"
    }
  },
  "rooms": {
    "HN-531": {
      "_id": "HN-531",
      "displayName": "HTR01 - HN-531",
      "id": "HN-531"
    },
    "HW-W113": {
      "_id": "HW-W113",
      "displayName": "HTR01 - HW-W113",
      "id": "HW-W113"
    }
  }
}
